procol-0.1.2.dist-info/METADATA
procol-0.1.2.dist-info/WHEEL
procol-0.1.2.dist-info/licenses/LICENSE
procol/__init__.py
procol/procol.cpython-312-x86_64-linux-gnu.so
procol-0.1.2.dist-info/RECORD
